{
  "mode": "STATIC",
  "locale": "en",
  "items": [
    { "id": "section-start", "kind": "header", "label": "Start Here" },
    { "id": "home", "kind": "link", "label": "Home", "icon": "mdi-home", "path": "home" },
    { "id": "getting-started", "kind": "link", "label": "Getting Started", "icon": "mdi-rocket", "path": "getting-started" },

    { "id": "section-editor", "kind": "header", "label": "Editor" },
    { "id": "editor", "kind": "link", "label": "Visual Editor", "icon": "mdi-pencil", "path": "editor" },
    { "id": "editor-nodes", "kind": "link", "label": "Node Reference", "icon": "mdi-view-list", "path": "editor/node-reference" },
    { "id": "editor-variables", "kind": "link", "label": "Variables and Data", "icon": "mdi-database", "path": "editor/variables" },
    { "id": "editor-simulation", "kind": "link", "label": "Verification and Simulation", "icon": "mdi-play-circle", "path": "editor/simulation" },
    { "id": "editor-targets", "kind": "link", "label": "Target Runtimes", "icon": "mdi-monitor", "path": "editor/target-runtimes" },

    { "id": "section-runner", "kind": "header", "label": "Runner" },
    { "id": "runner", "kind": "link", "label": "Runner and Desktop App", "icon": "mdi-run-fast", "path": "runner" },
    { "id": "runner-installation", "kind": "link", "label": "Installation and Updates", "icon": "mdi-download", "path": "runner/installation" },
    { "id": "runner-scripts", "kind": "link", "label": "Script Management", "icon": "mdi-file-document", "path": "runner/quick-start" },
    { "id": "runner-cli", "kind": "link", "label": "CLI Reference", "icon": "mdi-console", "path": "runner/cli-reference" },
    { "id": "runner-config", "kind": "link", "label": "Configuration and Devices", "icon": "mdi-cog", "path": "runner/configuration" },
    { "id": "runner-service", "kind": "link", "label": "Service and Triggers", "icon": "mdi-server", "path": "runner/background-service" },
    { "id": "runner-secrets", "kind": "link", "label": "Secrets", "icon": "mdi-key", "path": "runner/secrets" },
    { "id": "runner-storage", "kind": "link", "label": "Runs, Logs, and Help", "icon": "mdi-history", "path": "runner/storage-logs" },

    { "id": "section-package", "kind": "header", "label": "Package and Security" },
    { "id": "package-format", "kind": "link", "label": "BBS Package Format", "icon": "mdi-package-variant", "path": "package-format" },
    { "id": "security", "kind": "link", "label": "Security Model", "icon": "mdi-shield-check", "path": "security" },

    { "id": "section-deployment", "kind": "header", "label": "Deployment" },
    { "id": "deployment", "kind": "link", "label": "Deployment Guide", "icon": "mdi-cloud-upload", "path": "deployment" },

    { "id": "section-developers", "kind": "header", "label": "Developers" },
    { "id": "developers", "kind": "link", "label": "Developer Overview", "icon": "mdi-code-braces", "path": "developers" },
    { "id": "developers-setup", "kind": "link", "label": "Contributing and Setup", "icon": "mdi-tools", "path": "developers/setup" },
    { "id": "developers-editor", "kind": "link", "label": "Editor and Package Development", "icon": "mdi-pencil", "path": "developers/editor" },
    { "id": "developers-runner", "kind": "link", "label": "Runner Development", "icon": "mdi-cog", "path": "developers/runner" },
    { "id": "developers-wiki", "kind": "link", "label": "Wiki Documentation", "icon": "mdi-book-open", "path": "developers/wiki-documentation" },
    { "id": "developers-releases", "kind": "link", "label": "Release Engineering", "icon": "mdi-tag", "path": "developers/releases" }
  ]
}
